Workbook

Sheet Executive Dashboard
B2: RETAIL SALES & PROFITABILITY EXECUTIVE DASHBOARD
B3: Dataset: Superstore Commercial Retail Portfolio | Microsoft Excel 2021 Edition
B5: Total Sales | D5: Total Profit | F5: Profit Margin | H5: Total Orders | J5: Total Units Sold
B6: =SUM('Orders Data'!R2:R10000) | D6: =SUM('Orders Data'!U2:U10000) | F6: =D6/B6 | H6: =COUNT('Orders Data'!A2:A10000) | J6: =SUM('Orders Data'!S2:S10000)
B9: Category Financial Performance Summary | H9: Regional Sales Breakdown
B10: Category | C10: Total Sales | D10: Total Profit | E10: Profit Margin | F10: Units Sold | H10: Region | I10: Total Sales | J10: Total Profit | K10: Margin
B11: Furniture | C11: =SUMIFS('Orders Data'!R:R, 'Orders Data'!O:O, B11) | D11: =SUMIFS('Orders Data'!U:U, 'Orders Data'!O:O, B11) | E11: =D11/C11 | F11: =SUMIFS('Orders Data'!S:S, 'Orders Data'!O:O, B11) | H11: West | I11: =SUMIFS('Orders Data'!R:R, 'Orders Data'!M:M, H11) | J11: =SUMIFS('Orders Data'!U:U, 'Orders Data'!M:M, H11) | K11: =J11/I11
B12: Office Supplies | C12: =SUMIFS('Orders Data'!R:R, 'Orders Data'!O:O, B12) | D12: =SUMIFS('Orders Data'!U:U, 'Orders Data'!O:O, B12) | E12: =D12/C12 | F12: =SUMIFS('Orders Data'!S:S, 'Orders Data'!O:O, B12) | H12: East | I12: =SUMIFS('Orders Data'!R:R, 'Orders Data'!M:M, H12) | J12: =SUMIFS('Orders Data'!U:U, 'Orders Data'!M:M, H12) | K12: =J12/I12
B13: Technology | C13: =SUMIFS('Orders Data'!R:R, 'Orders Data'!O:O, B13) | D13: =SUMIFS('Orders Data'!U:U, 'Orders Data'!O:O, B13) | E13: =D13/C13 | F13: =SUMIFS('Orders Data'!S:S, 'Orders Data'!O:O, B13) | H13: Central | I13: =SUMIFS('Orders Data'!R:R, 'Orders Data'!M:M, H13) | J13: =SUMIFS('Orders Data'!U:U, 'Orders Data'!M:M, H13) | K13: =J13/I13
H14: South | I14: =SUMIFS('Orders Data'!R:R, 'Orders Data'!M:M, H14) | J14: =SUMIFS('Orders Data'!U:U, 'Orders Data'!M:M, H14) | K14: =J14/I14

Sheet Monthly Trends
B2: MONTHLY SALES & PROFITABILITY TIME-SERIES
B4: Year-Month | C4: Sales | D4: Profit | E4: Profit Margin | F4: Orders Count
B5: 2015-01 | C5: =SUMIFS('Orders Data'!R:R, 'Orders Data'!W:W, B5) | D5: =SUMIFS('Orders Data'!U:U, 'Orders Data'!W:W, B5) | E5: =D5/C5 | F5: =COUNTIFS('Orders Data'!W:W, B5)
B6: 2015-02 | C6: =SUMIFS('Orders Data'!R:R, 'Orders Data'!W:W, B6) | D6: =SUMIFS('Orders Data'!U:U, 'Orders Data'!W:W, B6) | E6: =D6/C6 | F6: =COUNTIFS('Orders Data'!W:W, B6)
B7: 2015-03 | C7: =SUMIFS('Orders Data'!R:R, 'Orders Data'!W:W, B7) | D7: =SUMIFS('Orders Data'!U:U, 'Orders Data'!W:W, B7) | E7: =D7/C7 | F7: =COUNTIFS('Orders Data'!W:W, B7)
B8: 2015-04 | C8: =SUMIFS('Orders Data'!R:R, 'Orders Data'!W:W, B8) | D8: =SUMIFS('Orders Data'!U:U, 'Orders Data'!W:W, B8) | E8: =D8/C8 | F8: =COUNTIFS('Orders Data'!W:W, B8)
B9: 2015-05 | C9: =SUMIFS('Orders Data'!R:R, 'Orders Data'!W:W, B9) | D9: =SUMIFS('Orders Data'!U:U, 'Orders Data'!W:W, B9) | E9: =D9/C9 | F9: =COUNTIFS('Orders Data'!W:W, B9)
B10: 2015-06 | C10: =SUMIFS('Orders Data'!R:R, 'Orders Data'!W:W, B10) | D10: =SUMIFS('Orders Data'!U:U, 'Orders Data'!W:W, B10) | E10: =D10/C10 | F10: =COUNTIFS('Orders Data'!W:W, B10)
B11: 2015-07 | C11: =SUMIFS('Orders Data'!R:R, 'Orders Data'!W:W, B11) | D11: =SUMIFS('Orders Data'!U:U, 'Orders Data'!W:W, B11) | E11: =D11/C11 | F11: =COUNTIFS('Orders Data'!W:W, B11)
B12: 2015-08 | C12: =SUMIFS('Orders Data'!R:R, 'Orders Data'!W:W, B12) | D12: =SUMIFS('Orders Data'!U:U, 'Orders Data'!W:W, B12) | E12: =D12/C12 | F12: =COUNTIFS('Orders Data'!W:W, B12)
B13: 2015-09 | C13: =SUMIFS('Orders Data'!R:R, 'Orders Data'!W:W, B13) | D13: =SUMIFS('Orders Data'!U:U, 'Orders Data'!W:W, B13) | E13: =D13/C13 | F13: =COUNTIFS('Orders Data'!W:W, B13)
B14: 2015-10 | C14: =SUMIFS('Orders Data'!R:R, 'Orders Data'!W:W, B14) | D14: =SUMIFS('Orders Data'!U:U, 'Orders Data'!W:W, B14) | E14: =D14/C14 | F14: =COUNTIFS('Orders Data'!W:W, B14)
B15: 2015-11 | C15: =SUMIFS('Orders Data'!R:R, 'Orders Data'!W:W, B15) | D15: =SUMIFS('Orders Data'!U:U, 'Orders Data'!W:W, B15) | E15: =D15/C15 | F15: =COUNTIFS('Orders Data'!W:W, B15)
B16: 2015-12 | C16: =SUMIFS('Orders Data'!R:R, 'Orders Data'!W:W, B16) | D16: =SUMIFS('Orders Data'!U:U, 'Orders Data'!W:W, B16) | E16: =D16/C16 | F16: =COUNTIFS('Orders Data'!W:W, B16)
... B52: 2018-12 | C52: =SUMIFS('Orders Data'!R:R, 'Orders Data'!W:W, B52) | D52: =SUMIFS('Orders Data'!U:U, 'Orders Data'!W:W, B52) | E52: =D52/C52 | F52: =COUNTIFS('Orders Data'!W:W, B52)

Sheet Sub-Category Breakdown
B2: SUB-CATEGORY PERFORMANCE & STATUS FLAGS
B4: Sub-Category | C4: Category | D4: Sales | E4: Profit | F4: Margin % | G4: Status Flag
B5: Accessories | C5: =XLOOKUP(B5, 'Orders Data'!P:P, 'Orders Data'!O:O, "Unknown") | D5: =SUMIFS('Orders Data'!R:R, 'Orders Data'!P:P, B5) | E5: =SUMIFS('Orders Data'!U:U, 'Orders Data'!P:P, B5) | F5: =E5/D5 | G5: =IF(E5>0, "Profitable", "Loss-Making")
B6: Appliances | C6: =XLOOKUP(B6, 'Orders Data'!P:P, 'Orders Data'!O:O, "Unknown") | D6: =SUMIFS('Orders Data'!R:R, 'Orders Data'!P:P, B6) | E6: =SUMIFS('Orders Data'!U:U, 'Orders Data'!P:P, B6) | F6: =E6/D6 | G6: =IF(E6>0, "Profitable", "Loss-Making")
B7: Art | C7: =XLOOKUP(B7, 'Orders Data'!P:P, 'Orders Data'!O:O, "Unknown") | D7: =SUMIFS('Orders Data'!R:R, 'Orders Data'!P:P, B7) | E7: =SUMIFS('Orders Data'!U:U, 'Orders Data'!P:P, B7) | F7: =E7/D7 | G7: =IF(E7>0, "Profitable", "Loss-Making")
B8: Binders | C8: =XLOOKUP(B8, 'Orders Data'!P:P, 'Orders Data'!O:O, "Unknown") | D8: =SUMIFS('Orders Data'!R:R, 'Orders Data'!P:P, B8) | E8: =SUMIFS('Orders Data'!U:U, 'Orders Data'!P:P, B8) | F8: =E8/D8 | G8: =IF(E8>0, "Profitable", "Loss-Making")
B9: Bookcases | C9: =XLOOKUP(B9, 'Orders Data'!P:P, 'Orders Data'!O:O, "Unknown") | D9: =SUMIFS('Orders Data'!R:R, 'Orders Data'!P:P, B9) | E9: =SUMIFS('Orders Data'!U:U, 'Orders Data'!P:P, B9) | F9: =E9/D9 | G9: =IF(E9>0, "Profitable", "Loss-Making")
B10: Chairs | C10: =XLOOKUP(B10, 'Orders Data'!P:P, 'Orders Data'!O:O, "Unknown") | D10: =SUMIFS('Orders Data'!R:R, 'Orders Data'!P:P, B10) | E10: =SUMIFS('Orders Data'!U:U, 'Orders Data'!P:P, B10) | F10: =E10/D10 | G10: =IF(E10>0, "Profitable", "Loss-Making")
B11: Copiers | C11: =XLOOKUP(B11, 'Orders Data'!P:P, 'Orders Data'!O:O, "Unknown") | D11: =SUMIFS('Orders Data'!R:R, 'Orders Data'!P:P, B11) | E11: =SUMIFS('Orders Data'!U:U, 'Orders Data'!P:P, B11) | F11: =E11/D11 | G11: =IF(E11>0, "Profitable", "Loss-Making")
B12: Envelopes | C12: =XLOOKUP(B12, 'Orders Data'!P:P, 'Orders Data'!O:O, "Unknown") | D12: =SUMIFS('Orders Data'!R:R, 'Orders Data'!P:P, B12) | E12: =SUMIFS('Orders Data'!U:U, 'Orders Data'!P:P, B12) | F12: =E12/D12 | G12: =IF(E12>0, "Profitable", "Loss-Making")
B13: Fasteners | C13: =XLOOKUP(B13, 'Orders Data'!P:P, 'Orders Data'!O:O, "Unknown") | D13: =SUMIFS('Orders Data'!R:R, 'Orders Data'!P:P, B13) | E13: =SUMIFS('Orders Data'!U:U, 'Orders Data'!P:P, B13) | F13: =E13/D13 | G13: =IF(E13>0, "Profitable", "Loss-Making")
B14: Furnishings | C14: =XLOOKUP(B14, 'Orders Data'!P:P, 'Orders Data'!O:O, "Unknown") | D14: =SUMIFS('Orders Data'!R:R, 'Orders Data'!P:P, B14) | E14: =SUMIFS('Orders Data'!U:U, 'Orders Data'!P:P, B14) | F14: =E14/D14 | G14: =IF(E14>0, "Profitable", "Loss-Making")
B15: Labels | C15: =XLOOKUP(B15, 'Orders Data'!P:P, 'Orders Data'!O:O, "Unknown") | D15: =SUMIFS('Orders Data'!R:R, 'Orders Data'!P:P, B15) | E15: =SUMIFS('Orders Data'!U:U, 'Orders Data'!P:P, B15) | F15: =E15/D15 | G15: =IF(E15>0, "Profitable", "Loss-Making")
B16: Machines | C16: =XLOOKUP(B16, 'Orders Data'!P:P, 'Orders Data'!O:O, "Unknown") | D16: =SUMIFS('Orders Data'!R:R, 'Orders Data'!P:P, B16) | E16: =SUMIFS('Orders Data'!U:U, 'Orders Data'!P:P, B16) | F16: =E16/D16 | G16: =IF(E16>0, "Profitable", "Loss-Making")
... B21: Tables | C21: =XLOOKUP(B21, 'Orders Data'!P:P, 'Orders Data'!O:O, "Unknown") | D21: =SUMIFS('Orders Data'!R:R, 'Orders Data'!P:P, B21) | E21: =SUMIFS('Orders Data'!U:U, 'Orders Data'!P:P, B21) | F21: =E21/D21 | G21: =IF(E21>0, "Profitable", "Loss-Making")

Sheet Orders Data
A1: Row ID | B1: Order ID | C1: Order Date | D1: Ship Date | E1: Ship Mode | F1: Customer ID | G1: Customer Name | H1: Segment | I1: Country | J1: City | K1: State | L1: Postal Code | M1: Region | N1: Product ID | O1: Category | P1: Sub-Category | Q1: Product Name | R1: Sales | S1: Quantity | T1: Discount | U1: Profit | V1: Order Year | W1: Order YearMonth | X1: Cost | Y1: Profit Margin
A2: 1 | B2: CA-2017-152156 | C2: 2017-11-08 | D2: 2017-11-11 | E2: Second Class | F2: CG-12520 | G2: Claire Gute | H2: Consumer | I2: United States | J2: Henderson | K2: Kentucky | L2: 42420.0 | M2: South | N2: FUR-BO-10001798 | O2: Furniture | P2: Bookcases | Q2: Bush Somerset Collection Bookcase | R2: 261.96 | S2: 2 | T2: 0 | U2: 41.9136 | V2: 2017 | W2: 2017-11 | X2: =R2-U2 | Y2: =U2/R2
A3: 2 | B3: CA-2017-152156 | C3: 2017-11-08 | D3: 2017-11-11 | E3: Second Class | F3: CG-12520 | G3: Claire Gute | H3: Consumer | I3: United States | J3: Henderson | K3: Kentucky | L3: 42420.0 | M3: South | N3: FUR-CH-10000454 | O3: Furniture | P3: Chairs | Q3: Hon Deluxe Fabric Upholstered Stacking Chairs, Rounded Back | R3: 731.94 | S3: 3 | T3: 0 | U3: 219.582 | V3: 2017 | W3: 2017-11 | X3: =R3-U3 | Y3: =U3/R3
A4: 3 | B4: CA-2017-138688 | C4: 2017-06-12 | D4: 2017-06-16 | E4: Second Class | F4: DV-13045 | G4: Darrin Van Huff | H4: Corporate | I4: United States | J4: Los Angeles | K4: California | L4: 90036.0 | M4: West | N4: OFF-LA-10000240 | O4: Office Supplies | P4: Labels | Q4: Self-Adhesive Address Labels for Typewriters by Universal | R4: 14.62 | S4: 2 | T4: 0 | U4: 6.8714 | V4: 2017 | W4: 2017-06 | X4: =R4-U4 | Y4: =U4/R4
A5: 4 | B5: US-2016-108966 | C5: 2016-10-11 | D5: 2016-10-18 | E5: Standard Class | F5: SO-20335 | G5: Sean O'Donnell | H5: Consumer | I5: United States | J5: Fort Lauderdale | K5: Florida | L5: 33311.0 | M5: South | N5: FUR-TA-10000577 | O5: Furniture | P5: Tables | Q5: Bretford CR4500 Series Slim Rectangular Table | R5: 957.5775 | S5: 5 | T5: 0.45 | U5: -383.031 | V5: 2016 | W5: 2016-10 | X5: =R5-U5 | Y5: =U5/R5
A6: 5 | B6: US-2016-108966 | C6: 2016-10-11 | D6: 2016-10-18 | E6: Standard Class | F6: SO-20335 | G6: Sean O'Donnell | H6: Consumer | I6: United States | J6: Fort Lauderdale | K6: Florida | L6: 33311.0 | M6: South | N6: OFF-ST-10000760 | O6: Office Supplies | P6: Storage | Q6: Eldon Fold 'N Roll Cart System | R6: 22.368 | S6: 2 | T6: 0.2 | U6: 2.5164 | V6: 2016 | W6: 2016-10 | X6: =R6-U6 | Y6: =U6/R6
A7: 6 | B7: CA-2015-115812 | C7: 2015-06-09 | D7: 2015-06-14 | E7: Standard Class | F7: BH-11710 | G7: Brosina Hoffman | H7: Consumer | I7: United States | J7: Los Angeles | K7: California | L7: 90032.0 | M7: West | N7: FUR-FU-10001487 | O7: Furniture | P7: Furnishings | Q7: Eldon Expressions Wood and Plastic Desk Accessories, Cherry Wood | R7: 48.86 | S7: 7 | T7: 0 | U7: 14.1694 | V7: 2015 | W7: 2015-06 | X7: =R7-U7 | Y7: =U7/R7
A8: 7 | B8: CA-2015-115812 | C8: 2015-06-09 | D8: 2015-06-14 | E8: Standard Class | F8: BH-11710 | G8: Brosina Hoffman | H8: Consumer | I8: United States | J8: Los Angeles | K8: California | L8: 90032.0 | M8: West | N8: OFF-AR-10002833 | O8: Office Supplies | P8: Art | Q8: Newell 322 | R8: 7.28 | S8: 4 | T8: 0 | U8: 1.9656 | V8: 2015 | W8: 2015-06 | X8: =R8-U8 | Y8: =U8/R8
A9: 8 | B9: CA-2015-115812 | C9: 2015-06-09 | D9: 2015-06-14 | E9: Standard Class | F9: BH-11710 | G9: Brosina Hoffman | H9: Consumer | I9: United States | J9: Los Angeles | K9: California | L9: 90032.0 | M9: West | N9: TEC-PH-10002275 | O9: Technology | P9: Phones | Q9: Mitel 5320 IP Phone VoIP phone | R9: 907.152 | S9: 6 | T9: 0.2 | U9: 90.7152 | V9: 2015 | W9: 2015-06 | X9: =R9-U9 | Y9: =U9/R9
A10: 9 | B10: CA-2015-115812 | C10: 2015-06-09 | D10: 2015-06-14 | E10: Standard Class | F10: BH-11710 | G10: Brosina Hoffman | H10: Consumer | I10: United States | J10: Los Angeles | K10: California | L10: 90032.0 | M10: West | N10: OFF-BI-10003910 | O10: Office Supplies | P10: Binders | Q10: DXL Angle-View Binders with Locking Rings by Samsill | R10: 18.504 | S10: 3 | T10: 0.2 | U10: 5.7825 | V10: 2015 | W10: 2015-06 | X10: =R10-U10 | Y10: =U10/R10
A11: 10 | B11: CA-2015-115812 | C11: 2015-06-09 | D11: 2015-06-14 | E11: Standard Class | F11: BH-11710 | G11: Brosina Hoffman | H11: Consumer | I11: United States | J11: Los Angeles | K11: California | L11: 90032.0 | M11: West | N11: OFF-AP-10002892 | O11: Office Supplies | P11: Appliances | Q11: Belkin F5C206VTEL 6 Outlet Surge | R11: 114.9 | S11: 5 | T11: 0 | U11: 34.47 | V11: 2015 | W11: 2015-06 | X11: =R11-U11 | Y11: =U11/R11
A12: 11 | B12: CA-2015-115812 | C12: 2015-06-09 | D12: 2015-06-14 | E12: Standard Class | F12: BH-11710 | G12: Brosina Hoffman | H12: Consumer | I12: United States | J12: Los Angeles | K12: California | L12: 90032.0 | M12: West | N12: FUR-TA-10001539 | O12: Furniture | P12: Tables | Q12: Chromcraft Rectangular Conference Tables | R12: 1706.184 | S12: 9 | T12: 0.2 | U12: 85.3092 | V12: 2015 | W12: 2015-06 | X12: =R12-U12 | Y12: =U12/R12
A13: 12 | B13: CA-2015-115812 | C13: 2015-06-09 | D13: 2015-06-14 | E13: Standard Class | F13: BH-11710 | G13: Brosina Hoffman | H13: Consumer | I13: United States | J13: Los Angeles | K13: California | L13: 90032.0 | M13: West | N13: TEC-PH-10002033 | O13: Technology | P13: Phones | Q13: Konftel 250 Conference phone - Charcoal black | R13: 911.424 | S13: 4 | T13: 0.2 | U13: 68.3568 | V13: 2015 | W13: 2015-06 | X13: =R13-U13 | Y13: =U13/R13
... A9995: 9994 | B9995: CA-2018-119914 | C9995: 2018-05-04 | D9995: 2018-05-09 | E9995: Second Class | F9995: CC-12220 | G9995: Chris Cortes | H9995: Consumer | I9995: United States | J9995: Westminster | K9995: California | L9995: 92683.0 | M9995: West | N9995: OFF-AP-10002684 | O9995: Office Supplies | P9995: Appliances | Q9995: Acco 7-Outlet Masterpiece Power Center, Wihtout Fax/Phone Line Protection | R9995: 243.16 | S9995: 2 | T9995: 0 | U9995: 72.948 | V9995: 2018 | W9995: 2018-05 | X9995: =R9995-U9995 | Y9995: =U9995/R9995

Sheet Data Quality & Dictionary
B2: SUPERSTORE DATA DICTIONARY & INTEGRITY AUDIT
B4: Field Name | C4: Data Type | D4: Excel Formula / Source | E4: Description
B5: Row ID | C5: Integer | D5: Direct source | E5: Unique sequential integer for each record line.
B6: Order ID | C6: String | D6: Direct source | E6: Unique alphanumeric transaction code.
B7: Order Date | C7: Date | D7: Direct source | E7: Date on which purchase order was placed.
B8: Ship Date | C8: Date | D8: Direct source | E8: Date on which carrier dispatched order.
B9: Ship Mode | C9: String | D9: Direct source | E9: Shipping service class (Standard, Second, First, Same Day).
B10: Customer Name | C10: String | D10: Direct source | E10: Full name of retail client.
B11: Segment | C11: String | D11: Direct source | E11: Client market tier (Consumer, Corporate, Home Office).
B12: Region | C12: String | D12: Direct source | E12: Geographic US territory (West, East, Central, South).
B13: Category | C13: String | D13: Direct source | E13: Top-level merchandise category (Furniture, Office Supplies, Technology).
B14: Sub-Category | C14: String | D14: Direct source | E14: Granular product grouping (17 sub-categories).
B15: Sales | C15: Currency | D15: Direct source | E15: Gross revenue amount in USD ($).
... B18: Profit | C18: Currency | D18: Direct source | E18: Net earnings generated after costs ($).
B19: Cost | C19: Currency | D19: =Sales - Profit | E19: Inferred operational acquisition/fulfillment cost.
B20: Profit Margin | C20: Percentage | D20: =Profit / Sales | E20: Return on sales margin ratio.
